Workbook

Sheet RESUMEN_1
D2: FASE1 | F2: FASE2
A3: Row Labels | B3: Sum of ESTIMACION (DIAS) | C3: Sum of ESTIMACION (MESES) | D3: BACK | E3: FRONT | F3: FRONT | G3: BACK
A4: BACK | B4: 93 | C4: 4.65
A5: DASHBOARD | B5: 25.5 | C5: 1.275 | G5: 1.275
A6: GENERAL | B6: 30.5 | C6: 1.525 | D6: 1.525
A7: MOVIL | B7: 25.25 | C7: 1.2625 | D7: 1.2625
A8: VECTORPAI | B8: 11.75 | C8: 0.5875 | D8: 0.5875
A9: FRONT | B9: 69.5 | C9: 3.475
A10: DASHBOARD | B10: 31.5 | C10: 1.575 | F10: 1.575
A11: MOVIL | B11: 32.5 | C11: 1.625 | E11: 1.625
A12: VECTORPAI | B12: 5.5 | C12: 0.275 | E12: 0.28
A13: ARQ | B13: 5.5 | C13: 0.275
A14: GENERAL | B14: 5.5 | C14: 0.275 | E14: 0.28
A15: PRUE | B15: 15 | C15: 0.75
A16: GENERAL | B16: 15 | C16: 0.75 | D16: 0.75 | F16: 0.75
A17: LIB | B17: 11.25 | C17: 0.5625
A18: GENERAL | B18: 11.25 | C18: 0.5625 | D18: 0.5625
A19: Grand Total | B19: 194.25 | C19: 9.7125
D20: =SUM(D6:D19) -> 4.6875 | F20: =SUM(F4:F19) -> 2.325
D21: MAY-SEP 2025 | F21: OCT-NOV 2025
D22: APP | F22: DASHBOARD

Sheet RESUMEN_2
A3: Row Labels | B3: Sum of ESTIMACION (DIAS) | C3: Sum of ESTIMACION (MESES)
A4: DASHBOARD | B4: 57 | C4: 2.85
A5: BACK | B5: 25.5 | C5: 1.275
A6: FRONT | B6: 31.5 | C6: 1.575
A7: GENERAL | B7: 62.25 | C7: 3.1125
A8: BACK | B8: 30.5 | C8: 1.525
A9: ARQ | B9: 5.5 | C9: 0.275
A10: PRUE | B10: 15 | C10: 0.75
A11: LIB | B11: 11.25 | C11: 0.5625
A12: MOVIL | B12: 57.75 | C12: 2.8875
A13: BACK | B13: 25.25 | C13: 1.2625
A14: FRONT | B14: 32.5 | C14: 1.625
A15: VECTORPAI | B15: 17.25 | C15: 0.8625
... A18: Grand Total | B18: 194.25 | C18: 9.7125

Sheet ACTIVIDADES
A1: PLATAFORMA | B1: TIPO | C1: REQ | D1: PERFILES | E1: MODULO | F1: METODO | G1: HEADERS JWT | H1: SERVICIO | I1: DESCRIPCION | J1: FASE2 | K1: ESTIMACION (HRS) | L1: ESTIMACION (DIAS) | M1: ESTIMACION (MESES)
A2: GENERAL | B2: AWS | C2: BACK | I2: Script para dar de alta SuperUsurio para Adminisitrar Adminsitradores | K2: 8 | L2: =K2/8 -> 1 | M2: =L2/20 -> 0.05
A3: GENERAL | B3: AWS | C3: BACK | I3: Script para generar estructuras de tablas nuevas de base de datos y carga inicial de datos y catalogos | K3: 20 | L3: =K3/8 -> 2.5 | M3: =L3/20 -> 0.125
A4: GENERAL | B4: .NET | C4: BACK | I4: Ruteo de peticiones REST a distintas base de datos dependiendo del Origen solicitado | K4: 16 | L4: =K4/8 -> 2 | M4: =L4/20 -> 0.1 | O4: AWS LAMBDA
A5: GENERAL | B5: AWS | C5: BACK | I5: Preparar nuevo PROYECTO para este set de servicios | K5: 8 | L5: =K5/8 -> 1 | M5: =L5/20 -> 0.05
A6: GENERAL | B6: .NET | C6: BACK | I6: Preparar ejemplo de servicio base GET/PUT/POST/DEL, con manejo de sesion JWT, validaciones y bitacora; para replicar en el universo de servicios | K6: 16 | L6: =K6/8 -> 2 | M6: =L6/20 -> 0.1 | O6: AWS LAMBDA
A7: GENERAL | B7: .NET | C7: ARQ | I7: Preparar proceso asincrono para generar archivo JSON de empresa SOLO para la empresa con bandera ACTIVOAPP true (JAVA) | K7: 20 | L7: =K7/8 -> 2.5 | M7: =L7/20 -> 0.125
A8: GENERAL | B8: .NET | C8: BACK | I8: Realizar envio de archivo JSON a bucket S3 AWS de empresas | K8: 20 | L8: =K8/8 -> 2.5 | M8: =L8/20 -> 0.125
A9: GENERAL | B9: AWS | C9: BACK | I9: Prepara CDK cdk-apisvector-pai: apigateway, lambdas, sqs, s3 | K9: 8 | L9: =K9/8 -> 1 | M9: =L9/20 -> 0.05
A10: GENERAL | B10: AWS | C10: BACK | I10: Prepara CDK cdk-apisvector-pai: estructuras de tablas dynamodb, json empresa; estatus proceso sqs, etc | K10: 8 | L10: =K10/8 -> 1 | M10: =L10/20 -> 0.05
A11: GENERAL | B11: AWS | C11: BACK | I11: Prepara CDK cdk-apisvector-pai: apigateway's domain vectorpai.api.vectordev.com.mx | K11: 8 | L11: =K11/8 -> 1 | M11: =L11/20 -> 0.05
A12: GENERAL | B12: AWS | C12: BACK | I12: Prepara CDK cdk-apisvector-pai: CID con workflow de git (Continuous integration deployment) | K12: 16 | L12: =K12/8 -> 2 | M12: =L12/20 -> 0.1
A13: GENERAL | B13: AWS | C13: BACK | I13: Configuracion de correos de codigo de activacion y codigo de confirmacion, templates | K13: 16 | L13: =K13/8 -> 2 | M13: =L13/20 -> 0.1
A14: GENERAL | B14: AWS | C14: BACK | I14: Configuracion de Cognito, user pools | K14: 8 | L14: =K14/8 -> 1 | M14: =L14/20 -> 0.05
A15: GENERAL | B15: AWS | C15: BACK | I15: Tarea para depurar estatus retiros, etc (tareas asincronas con estatus o encolamiento de peticiones) | K15: 16 | L15: =K15/8 -> 2 | M15: =L15/20 -> 0.1
A16: GENERAL | B16: .NET | C16: ARQ | I16: Analisis arquitectura actual por incremento de volumen transaccional | K16: 8 | L16: =K16/8 -> 1 | M16: =L16/20 -> 0.05
A17: GENERAL | B17: .NET | C17: ARQ | I17: Analisis tema: de Manifiesto reactivo en .NET, revisar que el sistema no sea "bloqueante" | K17: 8 | L17: =K17/8 -> 1 | M17: =L17/20 -> 0.05
A18: GENERAL | B18: .NET | C18: ARQ | I18: API MANAGER? Autenticacion AWS/..NET (JWT) | K18: 8 | L18: =K18/8 -> 1 | M18: =L18/20 -> 0.05
... A23: GENERAL | B23: .NET | C23: BACK | I23: Mecanismo de autenticacion desde .NET hacia servicios AWS-lambda para pantallas superusuario (SSO?AWSSDK?) | K23: 16 | L23: =K23/8 -> 2 | M23: =L23/20 -> 0.1
A24: DASHBOARD | B24: LAMBDA/DYNAMODB/COGNITO | C24: BACK | D24: TODOS | E24: REGISTRO | F24: POST | H24: /api/v1/register?type=admin | I24: Servicio para registro de admin: correo, codigoactivacion | K24: 24 | L24: =K24/8 -> 3 | M24: =L24/20 -> 0.15
A25: DASHBOARD | B25: LAMBDA/DYNAMODB/COGNITO | C25: BACK | D25: TODOS | E25: REGISTRO | F25: POST | H25: /api/v1/register/submit?type=admin | I25: Servicio para registro de admin: codigo de confirmacion, pw, cpw | K25: 8 | L25: =K25/8 -> 1 | M25: =L25/20 -> 0.05
A26: DASHBOARD | B26: LAMBDA/COGNITO | C26: BACK | D26: TODOS | E26: LOGIN | F26: POST | H26: /api/v1/login?type=admin | I26: Servicio para login, lambda que se comunica con cognito, obtiene perfil, permisos, menus | K26: 24 | L26: =K26/8 -> 3 | M26: =L26/20 -> 0.15
A27: DASHBOARD | B27: LAMBDA/COGNITO | C27: BACK | D27: TODOS | E27: CERRAR SESION | F27: GET | H27: /api/v1/logout?type=admin | I27: Servicio para cerrar sesion, lambda que se comunica con cognito | K27: 4 | L27: =K27/8 -> 0.5 | M27: =L27/20 -> 0.025
A28: DASHBOARD | B28: LAMBDA/COGNITO | C28: BACK | D28: TODOS | E28: RECUPERACION | F28: POST | H28: /api/v1/recover?type=admin | I28: Servicio para recuperacion: email | K28: 8 | L28: =K28/8 -> 1 | M28: =L28/20 -> 0.05
A29: DASHBOARD | B29: LAMBDA/COGNITO | C29: BACK | D29: TODOS | E29: RECUPERACION | F29: POST | H29: /api/v1/recover/submit?type=admin | I29: Servicio para reuperacion: codigo de confirmacion, pw, cpw | K29: 4 | L29: =K29/8 -> 0.5 | M29: =L29/20 -> 0.025
A30: DASHBOARD | B30: LAMBDA/COGNITO | C30: BACK | D30: TODOS | E30: CAMBIO PW | F30: POST | H30: /api/v1/password/change?type=admin | I30: Servicio para actualizar contraseña | K30: 8 | L30: =K30/8 -> 1 | M30: =L30/20 -> 0.05
A31: DASHBOARD | B31: LAMBDA/DYNAMODB | C31: BACK | D31: TODOS | E31: SELECCIÓN EMPRESA | F31: GET | H31: /api/v1/admin/companies | I31: Servicio para obtener las empresas a las tiene acceso el adminsitrador | K31: 8 | L31: =K31/8 -> 1 | M31: =L31/20 -> 0.05
A32: DASHBOARD | B32: .NET | C32: BACK | D32: TODOS | E32: SELECCIÓN EMPRESA | F32: GET | H32: /api/v1/admin/companies | I32: Servicio para obtener las empresas a las tiene acceso el adminsitrador | K32: 8 | L32: =K32/8 -> 1 | M32: =L32/20 -> 0.05 | N32: Recibe listado de contratos relac
A33: DASHBOARD | B33: LAMBDA/DYNAMODB/.NET | C33: BACK | D33: TODOS | E33: EMPRESA: DASHBOARD | F33: POST | H33: /api/v1/admin/company/dashboard? | I33: Servicio para obtener resumen dashboard de una empresa | J33: 1 | K33: 8 | L33: =K33/8 -> 1 | M33: =L33/20 -> 0.05
A34: DASHBOARD | B34: LAMBDA/DYNAMODB | C34: BACK | D34: TODOS | E34: EMPRESA: PARTICIPANTES | F34: GET | H34: /api/v1/admin/company/persons? | I34: Servicio para consultar participantes de una empresa y sus estatus de activacion; considerar paginacion (10x10) | K34: 16 | L34: =K34/8 -> 2 | M34: =L34/20 -> 0.1
A35: DASHBOARD | B35: .NET | C35: BACK | D35: TODOS | E35: EMPRESA: PARTICIPANTES | F35: GET | H35: /api/v1/admin/company/persons? | I35: Servicio para consultar participantes de una empresa y sus estatus de activacion | K35: 8 | L35: =K35/8 -> 1 | M35: =L35/20 -> 0.05
A36: DASHBOARD | B36: LAMBDA/DYNAMODB | C36: BACK | D36: TODOS | E36: EMPRESA: PARTICIPANTES | F36: POST | H36: /api/v1/admin/company/persons/activate? | I36: Servicio para activar participantes de manera masiva, y lanzar correo de activacion | K36: 24 | L36: =K36/8 -> 3 | M36: =L36/20 -> 0.15
A37: DASHBOARD | B37: LAMBDA/DYNAMODB | C37: BACK | D37: TODOS | E37: EMPRESA: PARTICIPANTES | F37: POST | H37: /api/v1/admin/company/person/activate? | I37: Servicio para activar participantes de manera individual, y lanzar correo de activacion | K37: 8 | L37: =K37/8 -> 1 | M37: =L37/20 -> 0.05
A38: DASHBOARD | B38: LAMBDA/DYNAMODB | C38: BACK | D38: TODOS | E38: EMPRESA: PARTICIPANTES | F38: PUT | H38: /api/v1/admin/company/person? | I38: Servicio para actualizar participante de manera individual: bloqueo, inactivar | K38: 8 | L38: =K38/8 -> 1 | M38: =L38/20 -> 0.05
A39: DASHBOARD | B39: LAMBDA/DYNAMODB | C39: BACK | D39: SISTEMAS/VECTOR | E39: EMPRESA: SERVICIOS | F39: GET | H39: /api/v1/admin/company/services? | I39: Servicio para obtener los servicios de la empresa | J39: 1 | K39: 8 | L39: =K39/8 -> 1 | M39: =L39/20 -> 0.05
A40: DASHBOARD | B40: LAMBDA/DYNAMODB | C40: BACK | D40: SISTEMAS/VECTOR | E40: EMPRESA: SERVICIOS | F40: PUT | H40: /api/v1/admin/company/service? | I40: Servicio para ACTIVAR O DESACTIVAR serviciio de la empresa | J40: 1 | K40: 4 | L40: =K40/8 -> 0.5 | M40: =L40/20 -> 0.025
A41: DASHBOARD | B41: LAMBDA/DYNAMODB | C41: BACK | D41: TODOS | E41: EMPRESA: CONFIGURACION: PARAMETROS | F41: GET | H41: /api/v1/admin/company/config/params? | I41: Servicio para obtener la configuracion de la empresa: aviso, mensaje, bloqueo, etc | K41: 8 | L41: =K41/8 -> 1 | M41: =L41/20 -> 0.05
A42: DASHBOARD | B42: LAMBDA/DYNAMODB | C42: BACK | D42: TODOS | E42: EMPRESA: CONFIGURACION: PARAMETROS | F42: POST | H42: /api/v1/admin/company/config/params? | I42: Servicio para actualizar la configuracion de la empresa: aviso, mensaje, bloqueo, etc | K42: 4 | L42: =K42/8 -> 0.5 | M42: =L42/20 -> 0.025
A43: DASHBOARD | B43: LAMBDA/DYNAMODB | C43: BACK | D43: TODOS | E43: EMPRESA: CONFIGURACION: LOOKANDFEEL | F43: GET | H43: /api/v1/admin/company/config/lookandfeel? | I43: Servicio para obtener la configuracion branding de la empresa | K43: 8 | L43: =K43/8 -> 1 | M43: =L43/20 -> 0.05
A44: DASHBOARD | B44: LAMBDA/DYNAMODB | C44: BACK | D44: TODOS | E44: EMPRESA: CONFIGURACION: LOOKANDFEEL | F44: POST | H44: /api/v1/admin/company/config/lookandfeel? | I44: Servicio para actualizar la configuracion branding de la empresa | K44: 4 | L44: =K44/8 -> 0.5 | M44: =L44/20 -> 0.025
A45: VECTORPAI | B45: LAMBDA/DYNAMODB | C45: BACK | D45: SISTEMAS/VECTOR | E45: MODULO GRUPOS DE EMPRESAS | F45: GET | H45: /api/v1/admin/config/groups? | I45: Servicio para obtener los grupos | K45: 4 | L45: =K45/8 -> 0.5 | M45: =L45/20 -> 0.025
A46: VECTORPAI | B46: LAMBDA/DYNAMODB | C46: BACK | D46: SISTEMAS/VECTOR | E46: MODULO GRUPOS DE EMPRESAS | F46: GET | H46: /api/v1/admin/config/group/contracts? | I46: Servicio para obtener contratos de un grupo | K46: 4 | L46: =K46/8 -> 0.5 | M46: =L46/20 -> 0.025
A47: VECTORPAI | B47: LAMBDA/DYNAMODB | C47: BACK | D47: SISTEMAS/VECTOR | E47: MODULO GRUPOS DE EMPRESAS | F47: POST | H47: /api/v1/admin/config/group? | I47: Servicio para agregar contrato(s) a un grupo de empres | K47: 8 | L47: =K47/8 -> 1 | M47: =L47/20 -> 0.05
A48: VECTORPAI | B48: LAMBDA/DYNAMODB | C48: BACK | D48: SISTEMAS/VECTOR | E48: MODULO GRUPOS DE EMPRESAS | F48: PUT | H48: /api/v1/admin/config/group? | I48: Servicio para actualizar grupo: nombre, activo, bloqueo,etc | K48: 4 | L48: =K48/8 -> 0.5 | M48: =L48/20 -> 0.025
A49: VECTORPAI | B49: LAMBDA/DYNAMODB | C49: BACK | D49: SISTEMAS/VECTOR | E49: MODULO ADMINISTRADORES | F49: GET | H49: /api/v1/admin/config/group/admins? | I49: Servicio para obtener Adminsitradores: idadmin, nombre, grupo, contrato | K49: 8 | L49: =K49/8 -> 1 | M49: =L49/20 -> 0.05
A50: VECTORPAI | B50: LAMBDA/DYNAMODB | C50: BACK | D50: SISTEMAS/VECTOR | E50: MODULO ADMINISTRADORES | F50: GET | H50: /api/v1/admin/config/groups? | I50: Servicio para obtener los grupos disponibles | K50: 4 | L50: =K50/8 -> 0.5 | M50: =L50/20 -> 0.025
A51: VECTORPAI | B51: LAMBDA/DYNAMODB | C51: BACK | D51: SISTEMAS/VECTOR | E51: MODULO ADMINISTRADORES | F51: GET | H51: /api/v1/admin/config/group/contracts? | I51: Servicio para obtener los contratos de un grupo seleccionado | K51: 4 | L51: =K51/8 -> 0.5 | M51: =L51/20 -> 0.025
A52: VECTORPAI | B52: LAMBDA/DYNAMODB | C52: BACK | D52: SISTEMAS/VECTOR | E52: MODULO ADMINISTRADORES | F52: POST | H52: /api/v1/admin/config/group/admin? | I52: Servicio para actualizar administrador-grupo-contrato, enviar codigo de activacion de admin | K52: 8 | L52: =K52/8 -> 1 | M52: =L52/20 -> 0.05
... A55: VECTORPAI | B55: LAMBDA/DYNAMODB | C55: BACK | D55: SISTEMAS/VECTOR | E55: MODULO PARAMETROS GLOBAL | F55: POST | H55: /api/v1/admin/config/params? | I55: Servicio para actualizar la configuracion global | K55: 4 | L55: =K55/8 -> 0.5 | M55: =L55/20 -> 0.025
A56: VECTORPAI | B56: LAMBDA/DYNAMODB | C56: BACK | D56: SISTEMAS/VECTOR | E56: CATALOGOS SCRIPTS | H56: NA | I56: Generar SCRIPT para carga inicial de catalogos X9 | K56: 8 | L56: =K56/8 -> 1 | M56: =L56/20 -> 0.05
A57: VECTORPAI | B57: LAMBDA/DYNAMODB | C57: BACK | D57: SISTEMAS/VECTOR | E57: MODULO BITACORA | F57: GET | H57: /api/v1/admin/bitacora | I57: Servicio para obtener registros de bitacora, con filtros de fecha/hora, correo, considerar paginacion (10x10); exportacion | J57: 1 | K57: 30 | L57: =K57/8 -> 3.75 | M57: =L57/20 -> 0.1875
A58: MOVIL | B58: LAMBDA/DYNAMODB/COGNITO | C58: BACK | D58: TODOS | E58: REGISTRO CAPTURA | F58: POST | H58: /api/v1/register?type=person | I58: Servicio para registro de participante: correo, codigoactivacion | K58: 12 | L58: =K58/8 -> 1.5 | M58: =L58/20 -> 0.075
A59: MOVIL | B59: LAMBDA/DYNAMODB/COGNITO | C59: BACK | D59: TODOS | E59: REGISTRO CONFIRMACION | F59: POST | H59: /api/v1/register/submit?type=person | I59: Servicio para registro de participante: codigo de confirmacion, pw, cpw | K59: 4 | L59: =K59/8 -> 0.5 | M59: =L59/20 -> 0.025
A60: MOVIL | B60: LAMBDA/COGNITO | C60: BACK | D60: TODOS | E60: LOGIN | F60: POST | H60: /api/v1/login?type=person | I60: Servicio para login, lambda que se comunica con cognito, obtiene perfil del usuario, y perfil de la empresa | K60: 12 | L60: =K60/8 -> 1.5 | M60: =L60/20 -> 0.075
A61: MOVIL | B61: LAMBDA/COGNITO | C61: BACK | D61: TODOS | E61: CERRAR SESION | F61: GET | H61: /api/v1/logout?type=person | I61: Servicio para cerrar sesion, lambda que se comunica con cognito | K61: 2 | L61: =K61/8 -> 0.25 | M61: =L61/20 -> 0.0125
A62: MOVIL | B62: LAMBDA/COGNITO | C62: BACK | D62: TODOS | E62: RECUPERACION: CAPTURA | F62: POST | H62: /api/v1/recover?type=person | I62: Servicio para recuperacion: email | K62: 4 | L62: =K62/8 -> 0.5 | M62: =L62/20 -> 0.025
A63: MOVIL | B63: LAMBDA/COGNITO | C63: BACK | D63: TODOS | E63: RECUPERACION: CONFIRMACION | F63: POST | H63: /api/v1/recover/submit?type=person | I63: Servicio para reuperacion: codigo de confirmacion, pw, cpw | K63: 2 | L63: =K63/8 -> 0.25 | M63: =L63/20 -> 0.0125
A64: MOVIL | B64: LAMBDA/COGNITO | C64: BACK | D64: TODOS | E64: CAMBIO PW | F64: POST | H64: /api/v1/password/change?type=person | I64: Servicio para actualizar contraseña | K64: 2 | L64: =K64/8 -> 0.25 | M64: =L64/20 -> 0.0125
A65: MOVIL | B65: LAMBDA/DYNAMODB | C65: BACK | D65: PARTICIPANTE | E65: SELECCIÓN EMPRESA | F65: GET | H65: /api/v1/enduser/sumary/companies? | I65: Servicio para obtener resumen de los contratos asociados al participante | K65: 4 | L65: =K65/8 -> 0.5 | M65: =L65/20 -> 0.025
A66: MOVIL | B66: LAMBDA/DYNAMODB | C66: BACK | D66: PARTICIPANTE | E66: SALDOS | F66: GET | H66: /api/v1/enduser/balance? | I66: Servicio para obtener saldo del participante y meta de ahorro | K66: 4 | L66: =K66/8 -> 0.5 | M66: =L66/20 -> 0.025
A67: MOVIL | B67: LAMBDA/DYNAMODB | C67: BACK | D67: PARTICIPANTE | E67: META AHORRO | F67: POST | H67: /api/v1/enduser/goal? | I67: Servicio para registrar meta de ahorro del participante | K67: 4 | L67: =K67/8 -> 0.5 | M67: =L67/20 -> 0.025
A68: MOVIL | B68: LAMBDA/DYNAMODB | C68: BACK | D68: PARTICIPANTE | E68: RESUMEN MOVS | F68: GET | H68: /api/v1/enduser/movs/sumary? | I68: Servicio para obtener resumen de movimientos | K68: 4 | L68: =K68/8 -> 0.5 | M68: =L68/20 -> 0.025
A69: MOVIL | B69: LAMBDA/DYNAMODB | C69: BACK | D69: PARTICIPANTE | E69: DETALLE MOVS | F69: GET | H69: /api/v1/enduser/movs/detail? | I69: Servicio para obtener DETALLE de movimientos | K69: 4 | L69: =K69/8 -> 0.5 | M69: =L69/20 -> 0.025
... A83: MOVIL | B83: LAMBDA/.NET | C83: BACK | D83: PARTICIPANTE | E83: RETIROS | F83: DELETE | H83: /api/v1/enduser/withdrawal/{idretiro} | I83: Servico para cancelar un retiro, solo permitir modificar en estatus "en revision" | K83: 8 | L83: =K83/8 -> 1 | M83: =L83/20 -> 0.05
A84: DASHBOARD | B84: REACT | C84: FRONT | D84: TODOS | E84: REGISTRO | I84: Pantalla para registro de admin: registro y confirmacion | K84: 8 | L84: =K84/8 -> 1 | M84: =L84/20 -> 0.05
A85: DASHBOARD | B85: REACT | C85: FRONT | D85: TODOS | E85: LOGIN | I85: Pantalla para realizar login, obtener token de sesion y perfil | K85: 8 | L85: =K85/8 -> 1 | M85: =L85/20 -> 0.05
A86: DASHBOARD | B86: REACT | C86: FRONT | D86: TODOS | E86: RECUPERACION | I86: Pantalla para relizar recuperacion de contraseña, captura | K86: 8 | L86: =K86/8 -> 1 | M86: =L86/20 -> 0.05
A87: DASHBOARD | B87: REACT | C87: FRONT | D87: TODOS | E87: GENERAL | I87: Manejo expiracion de sesion | K87: 16 | L87: =K87/8 -> 2 | M87: =L87/20 -> 0.1
A88: DASHBOARD | B88: REACT | C88: FRONT | D88: TODOS | E88: GENERAL | I88: Pantalla para presentar Mensaje Popup Aviso | J88: 1 | K88: 4 | L88: =K88/8 -> 0.5 | M88: =L88/20 -> 0.025
A89: DASHBOARD | B89: REACT | C89: FRONT | D89: TODOS | E89: GENERAL | I89: Banner Texto en la parte superior | J89: 1 | K89: 4 | L89: =K89/8 -> 0.5 | M89: =L89/20 -> 0.025
A90: DASHBOARD | B90: REACT | C90: FRONT | D90: TODOS | E90: GEOLOCALIZACION | I90: Pantalla para soliictar permiso y obtener geolocalizacion del usuario | J90: 1 | K90: 16 | L90: =K90/8 -> 2 | M90: =L90/20 -> 0.1
A91: DASHBOARD | B91: REACT | C91: FRONT | D91: TODOS | E91: CAMBIO PW | I91: Pantalla para realizar cambio de contraseña, revisar tema de password expirado cognito | K91: 8 | L91: =K91/8 -> 1 | M91: =L91/20 -> 0.05
A92: DASHBOARD | B92: REACT | C92: FRONT | D92: TODOS | E92: SELECCIÓN EMPRESA | I92: Pantalla para selección de empresa a las tiene acceso el adminsitrador | K92: 8 | L92: =K92/8 -> 1 | M92: =L92/20 -> 0.05
A93: DASHBOARD | B93: REACT | C93: FRONT | D93: TODOS | E93: MENU LATERAL | I93: Opcion para realizar cambio de contraseña/cierre sesion | K93: 8 | L93: =K93/8 -> 1 | M93: =L93/20 -> 0.05
A94: DASHBOARD | B94: REACT | C94: FRONT | D94: TODOS | E94: MENU LATERAL | I94: Presentar opciones del menu en base al perfil y empresa seleccionada, icono empresa | K94: 4 | L94: =K94/8 -> 0.5 | M94: =L94/20 -> 0.025
A95: DASHBOARD | B95: REACT | C95: FRONT | D95: TODOS | E95: EMPRESA: DASHBOARD | I95: Patnalla para presentar resumen dashboard de una empresa | J95: 1 | K95: 8 | L95: =K95/8 -> 1 | M95: =L95/20 -> 0.05
A96: DASHBOARD | B96: REACT | C96: FRONT | D96: TODOS | E96: EMPRESA: PARTICIPANTES | I96: Pantalla para consultar participantes de una empresa y sus estatus de activacion | K96: 8 | L96: =K96/8 -> 1 | M96: =L96/20 -> 0.05
A97: DASHBOARD | B97: REACT | C97: FRONT | D97: TODOS | E97: EMPRESA: PARTICIPANTES | I97: Pantalla para activar participantes de manera masiva | K97: 24 | L97: =K97/8 -> 3 | M97: =L97/20 -> 0.15
A98: DASHBOARD | B98: REACT | C98: FRONT | D98: TODOS | E98: EMPRESA: PARTICIPANTES | I98: Pantalla para activar participantes de manera individual | K98: 16 | L98: =K98/8 -> 2 | M98: =L98/20 -> 0.1
A99: DASHBOARD | B99: REACT | C99: FRONT | D99: TODOS | E99: EMPRESA: PARTICIPANTES | I99: Pantalla para actualizar participante de manera individual: bloqueo, inactivar | K99: 8 | L99: =K99/8 -> 1 | M99: =L99/20 -> 0.05
A100: DASHBOARD | B100: REACT | C100: FRONT | D100: SISTEMAS/VECTOR | E100: EMPRESA: SERVICIOS | I100: Pantalla para obtener los servicios de la empresa | J100: 1 | K100: 4 | L100: =K100/8 -> 0.5 | M100: =L100/20 -> 0.025
A101: DASHBOARD | B101: REACT | C101: FRONT | D101: SISTEMAS/VECTOR | E101: EMPRESA: SERVICIOS | I101: Pantalla para ACTIVAR O DESACTIVAR serviciio de la empresa | J101: 1 | K101: 4 | L101: =K101/8 -> 0.5 | M101: =L101/20 -> 0.025
A102: DASHBOARD | B102: REACT | C102: FRONT | D102: TODOS | E102: EMPRESA: CONFIGURACION: PARAMETROS | I102: Pantalla para presentar y actualizar la configuracion de la empresa: mensaje, aviso, bloqueo, etc | K102: 8 | L102: =K102/8 -> 1 | M102: =L102/20 -> 0.05
A103: DASHBOARD | B103: REACT | C103: FRONT | D103: TODOS | E103: EMPRESA: CONFIGURACION: LOOKANDFEEL | I103: Pantalla para presentar y actualizar la configuracion branding de la empresa | K103: 8 | L103: =K103/8 -> 1 | M103: =L103/20 -> 0.05
A104: DASHBOARD | B104: REACT | C104: FRONT | D104: NA | E104: GENERAL | I104: Configuracion de Proyecto REACT, git repositories | K104: 8 | L104: =K104/8 -> 1 | M104: =L104/20 -> 0.05
A105: DASHBOARD | B105: REACT | C105: FRONT | D105: NA | E105: GENERAL | I105: Configuracion de proyecto amplify pipilines DEV/QA/PROD vs Git | K105: 8 | L105: =K105/8 -> 1 | M105: =L105/20 -> 0.05
A106: DASHBOARD | B106: REACT | C106: FRONT | D106: NA | E106: GENERAL | I106: Configuracion base de servicios .env, Sagas, manejor de sesion JWT, resonsehandle, etc | K106: 40 | L106: =K106/8 -> 5 | M106: =L106/20 -> 0.25
A107: DASHBOARD | B107: REACT | C107: FRONT | D107: NA | E107: GENERAL | I107: Configuracion de HOST domain: DEV/QA/PROD | K107: 16 | L107: =K107/8 -> 2 | M107: =L107/20 -> 0.1
A108: VECTORPAI | B108: .NET GRAFICO | C108: FRONT | D108: SISTEMAS/VECTOR | E108: MODULO CATALOGO DE GRUPOS | I108: Modulo para AGREGAR grupo de contratos | K108: 4 | L108: =K108/8 -> 0.5 | M108: =L108/20 -> 0.025
A109: VECTORPAI | B109: .NET GRAFICO | C109: FRONT | D109: SISTEMAS/VECTOR | E109: MODULO CATALOGO DE GRUPOS | I109: Modulo para relacionar contratos a Grupos de Empresas | K109: 4 | L109: =K109/8 -> 0.5 | M109: =L109/20 -> 0.025
A110: VECTORPAI | B110: .NET GRAFICO | C110: FRONT | D110: SISTEMAS/VECTOR | E110: MODULO ADMINISTRADORES | I110: Modulo para asignar administradores a una grupo y/o contrato | K110: 4 | L110: =K110/8 -> 0.5 | M110: =L110/20 -> 0.025
A111: VECTORPAI | B111: .NET GRAFICO | C111: FRONT | D111: SISTEMAS/VECTOR | E111: MODULO ADMINISTRADORES | I111: Pantalla para actualizar adminsitradores de manera individual: bloqueo, inactivar | K111: 8 | L111: =K111/8 -> 1 | M111: =L111/20 -> 0.05
A112: VECTORPAI | B112: .NET GRAFICO | C112: FRONT | D112: SISTEMAS/VECTOR | E112: MODULO PARAMETROS | I112: Modulo bloquear acceso y colocar mensaje, banner o aviso | K112: 8 | L112: =K112/8 -> 1 | M112: =L112/20 -> 0.05
A113: VECTORPAI | B113: .NET GRAFICO | C113: FRONT | D113: SISTEMAS/VECTOR | E113: MODULO BITACORA | I113: Pantalla para presentar bitacora de acceso, con paginacion (10x10) y filtros | J113: 1 | K113: 16 | L113: =K113/8 -> 2 | M113: =L113/20 -> 0.1
A114: MOVIL | B114: REACT NATIVE | C114: FRONT | D114: NA | E114: GENERAL | I114: Configuracion base de servicios .env, Sagas, manejor de sesion JWT, resonsehandle, etc | K114: 40 | L114: =K114/8 -> 5 | M114: =L114/20 -> 0.25
A115: MOVIL | B115: REACT NATIVE | C115: FRONT | D115: PARTICIPANTE | E115: REGISTRO | I115: Pantalla para registro de admin: registro y confirmacion | K115: 8 | L115: =K115/8 -> 1 | M115: =L115/20 -> 0.05
A116: MOVIL | B116: REACT NATIVE | C116: FRONT | D116: PARTICIPANTE | E116: LOGIN | I116: Pantalla para realizar login, obtener token de sesion y perfil | K116: 8 | L116: =K116/8 -> 1 | M116: =L116/20 -> 0.05
A117: MOVIL | B117: REACT NATIVE | C117: FRONT | D117: PARTICIPANTE | E117: RECUPERACION | I117: Pantalla para relizar recuperacion de contraseña, captura | K117: 8 | L117: =K117/8 -> 1 | M117: =L117/20 -> 0.05
A118: MOVIL | B118: REACT NATIVE | C118: FRONT | D118: PARTICIPANTE | E118: GENERAL | I118: Manejo expiracion de sesion | K118: 16 | L118: =K118/8 -> 2 | M118: =L118/20 -> 0.1
A119: MOVIL | B119: REACT NATIVE | C119: FRONT | D119: PARTICIPANTE | E119: GENERAL | I119: Opcion para forzar actualizacion de app, por version vigente | K119: 8 | L119: =K119/8 -> 1 | M119: =L119/20 -> 0.05
...

Sheet BD_TABLES
A1: NUBE | B1: PREMISE
A5: cental1.PARTIPANTE
A6: CONTRATO | B6: IDEMPRESA | C6: IDPARTICIPANTE | D6: IDTOKENPARTICIPANTE | E6: NOMBRE PART
B7: 3050 | C7: 1234567943 | D7: ABC6451231364
B8: 3051 | C8: 6561231311 | D8: 41C6451231364
B9: 3058 | C9: 9121313133 | D9: DSADAS4D5A13
A11: CATALOGO EMPRESAS
A12: CONTRATO | B12: IDEMPRESA | C12: NOMBRE EMPRESA
A21: USUARIOUNICO (TABLA PUEDE ESTAR EN LA NUBE) | F21: DATOS USUARIO APP
A22: EMAIL | B22: IDUSUARIO_UNICO | C22: CODIGO ACTIVACION | D22: VIGENCIA_CODIGO_ACTIVACION | E22: COGNITO_SUB | F22: OSTYPE | G22: OSVERSION | H22: MODEL | I22: BLOQUEO | J22: MOTIVO BLOQUEO | K22: ESTATUS
A23: macastro@vector.com.mx | B23: 3e01db55-3f84-420f-aca5-031f07579b5b | C23: 912315 | D23: 45801 | E23: D1S2AD3AS1D23A1312323 | F23: ANDROID | G23: 16 | H23: XIAMI | K23: 2 | M23: 1ER REGISTRO
A24: pramirez@vector.com.mx | B24: 31312312-3f84-420f-aca5-031f07579b5b | C24: 81213123 | D24: 45801 | E24: 31JJLAKLDMAPDAS | F24: IOS | G24: 21 | H24: APPLE | K24: 2
A25: hrivera@vector.com.mx | B25: dkasldjlasdkasñlkdña | C25: 999999 | D25: 45801 | E25: djkasjdlkasjkldas | F25: IOS | G25: 21 | H25: APPLE | K25: 2 | L25: **SE GENERA CON SCRIPT
A27: ESTATUS REGISTRO (TABLA PUEDE ESTAR EN LA NUBE) | T27: 0
A28: 0 | B28: INACTIVO
A29: 1 | B29: REGISTRO
A30: 2 | B30: ACTIVO
A31: 9 | B31: BLOQUEO
A33: CAT_GRUPOS
A34: IDGRUPO | B34: ORIGEN | C34: GRUPO
A35: 1 | B35: LEAR | C35: G-LEAR
A36: 2 | B36: CENTRAL1 | C36: G-EMPRESAS VECTOR
A39: REL_GRUPO_CONTRATO
A40: IDGRUPO | B40: CONTRATO | C40: NOMBRE | D40: IDEMPRESA
A41: 1 | B41: 123456 | C41: Lear MTO | D41: 310
A42: 1 | B42: 654312 | C42: Lear ELECTRICAL | D42: 311
A43: 1 | B43: 753159 | C43: Lear PMO | D43: 315
A44: 2 | B44: 951357 | C44: CAHPAT | D44: 531
A45: 2 | B45: 682715 | C45: FONDOS EMPLEADOS | D45: 710
G48: CASO1: SELECCIÓN MANUAL | J48: CASO2: SELECCIÓN GRUPO TODOS | L48: CASO3: MODIFICAR
A49: REL_GRUPO_ADMIN_ACCESO | G49: SELECCIONA GRUPO: | H49: <G-LEAR> | J49: SELECCIONA GRUPO: | K49: <G-LEAR> | L49: SELECCIONA GRUPO: | M49: <G-LEAR>
A50: IDGRUPO | B50: CONTRATO | C50: IDUSUARIOUNICO (ADMIN/VECTOR/SISTEMAS) | E50: ACTIVO
A51: 1 | B51: 0 | C51: 3e01db55-3f84-420f-aca5-031f07579b5b | E51: 1 | F51: () | G51: SELECCIONA SELECCIONAR TODOS LOS CONTRATOS | I51: (x) | J51: SELECCIONA SELECCIONAR TODOS LOS CONTRATOS | K51: (x) | L51: SELECCIONA SELECCIONAR TODOS LOS CONTRATOS
A52: 1 | B52: 0 | C52: 31312312-3f84-420f-aca5-031f07579b5b | E52: 1 | F52: (x) | G52: SELECCION MANUAL | I52: () | J52: SELECCION MANUAL | K52: () | L52: SELECCION MANUAL
A53: 1 | B53: 654312 | C53: dkasldjlasdkasñlkdña | E53: 1 | G53: 123456 | H53: X | J53: 123456 | L53: 123456
A54: 1 | B54: 753159 | C54: dkasldjlasdkasñlkdña | E54: 1 | G54: 654312 | J54: 654312 | L54: 654312
A55: 2 | B55: 682715 | C55: dkasldjlasdkasñlkdña | E55: 0 | G55: 753159 | H55: X | J55: 753159 | L55: 753159
A58: MOTIVO BLOQUEO
A59: 1 | B59: ABC
A60: 2 | B60: ABC
A61: 3 | B61: ABC
A63: PERFILES
A64: 1 (SISTEMAS) | B64: **PUEDE VER TODOS LAS EMPRESAS EN DASHBOARD
A65: 2 (VECTOR) | B65: **PUEDE VER TODOS LAS EMPRESAS EN DASHBOARD
A66: 4 (EMPRESA) | B66: **PUEDE VER SOLO LAS EMPRESAS DONDE TENGA RELACION (REL_ORIGEN_EMPRESA_ADMIN_USUARIOUNICO )
A67: 5 (PART) | B67: **NO PUEDE ACCEDER A DASHBOARD
A70: IDUSUARIO_UNICO | B70: IDPERFIL
A71: 31312312-3f84-420f-aca5-031f07579b5b | B71: 1 (SISTEMAS)
A72: 31312312-3f84-420f-aca5-031f07579b5b | B72: 2 (VECTOR)
A73: 31312312-3f84-420f-aca5-031f07579b5b | B73: 4 (EMPRESA)
A74: 3e01db55-3f84-420f-aca5-031f07579b5b | B74: 5 (PART)
A75: dkasldjlasdkasñlkdña | B75: 4 (EMPRESA)
A77: PERFIL-MODULO
A78: PERFIL | B78: CONTEXTO | C78: MODULO
A79: 1 (SISTEMAS) | B79: DASHBOARD | C79: ADMIN-ADMINISTRADORES DE EMP | D79: **SE GENERA CON SCRIPT
A80: 1 (SISTEMAS) | B80: DASHBOARD | C80: ADMIN-ADMINISTRADORES DE EMP | D80: **SE GENERA CON SCRIPT
A81: 2 (VECTOR) | B81: DASHBOARD | C81: ADMIN-ADMINISTRADORES DE EMP | D81: **SE GENERA CON SCRIPT
A82: 2 (VECTOR) | B82: DASHBOARD | C82: ADMIN-ADMINISTRADORES DE EMP | D82: **SE GENERA CON SCRIPT
A83: 4 (EMPRESA) | B83: DASHBOARD | C83: EMPRESA-PARTICIPANTES | D83: **SE GENERA CON SCRIPT
A84: 4 (EMPRESA) | B84: DASHBOARD | C84: EMPRESA SERVICIOS
A85: 4 (EMPRESA) | B85: DASHBOARD | C85: EMPRESA BRANDING
A87: PERFIL-IDSERVICIO
A88: PERFIL | B88: IDSERVICIO | C88: ACTIVO
A89: 4 (EMPRESA) | B89: 10100 | C89: TRUE
A90: 4 (EMPRESA) | B90: 10110 | C90: FALSE
A91: 4 (EMPRESA) | B91: 10200 | C91: TRUE
A94: SERVICIOS
A95: GRUPO | B95: IDSERVICIO | C95: SERVICIO | D95: ACTIVO
B96: 10100 | C96: REGISTRO CAPTURA
B97: 10110 | C97: REGISTRO CONFIRMACION
B98: 10200 | C98: LOGIN
B99: 10300 | C99: CERRAR SESION
B100: 10400 | C100: RECUPERACION: CAPTURA
B101: 10410 | C101: RECUPERACION: CONFIRMACION
B102: 10500 | C102: CAMBIO PW
A105: REL_ORIGEN_EMPRESA_PARTICIPANTE_USUARIOUNICO (TABLA PUEDE ESTAR EN LA NUBE)
A106: ORIGEN | B106: GRUPO | C106: CONTRATO | D106: IDPARTICIPANTE | E106: IDUSUARIO_UNICO | F106: ACTIVO
A107: CENTRAL1 | B107: 2 | C107: 3050 | D107: 1234567943 | E107: 3e01db55-3f84-420f-aca5-031f07579b5b
A108: CENTRAL2 | B108: 7 | C108: 3051 | D108: 6561231311 | E108: 3e01db55-3f84-420f-aca5-031f07579b5b
A109: LEAR | B109: 1 | C109: 3051 | D109: 6561231311 | E109: 3e01db55-3f84-420f-aca5-031f07579b5b
A110: SORIANA | B110: 9 | C110: 3055 | D110: 6121321302 | E110: 3e01db55-3f84-420f-aca5-031f07579b5b
A112: REL_ORIGEN_EMPRESA_PARTICIPANTE_USUARIOUNICO (TABLA PUEDE ESTAR EN LA NUBE) (HISTORICO)
A113: ORIGEN | B113: GRUPO | C113: CONTRATO | D113: IDCICLO | E113: IDPARTICIPANTE | F113: IDUSUARIO_UNICO
A114: CENTRAL1 | B114: 2 | C114: 3050 | D114: 2 | E114: 1234567943 | F114: 3e01db55-3f84-420f-aca5-031f07579b5b
A115: CENTRAL2 | B115: 7 | C115: 3051 | D115: 15 | E115: 6561231311 | F115: 3e01db55-3f84-420f-aca5-031f07579b5b
A119: DAHSBOARD_EMPRESA_SERVICIOS
A120: ORIGEN | B120: CONTRATO | C120: SERVICIO
A121: CENTRAL1 | B121: 3050 | C121: RETIROS
A122: CENTRAL1 | B122: 3050 | C122: PRESTAMOS
A123: CENTRAL1 | B123: 3050 | C123: BAJA
A124: LEAR | B124: 3051 | C124: RETIROS
A126: DAHSBOARD_CONF_PARAMS_EMP
A127: ORIGEN | B127: CONTRATO | C127: PARAMETRO | D127: VALOR
A128: CENTRAL1 | B128: 3050 | C128: ACTIVO | D128: TRUE
A129: CENTRAL1 | B129: 3050 | C129: BLOQUEO | D129: TRUE
A130: CENTRAL1 | B130: 3050 | C130: MSG BLOQUEO | D130: ABC
A131: CENTRAL1 | B131: 3050 | C131: BANNER | D131: TRUE
A132: CENTRAL1 | B132: 3050 | C132: MSG BANNER | D132: ABC
A133: CENTRAL1 | B133: 3050 | C133: AVISO | D133: TRUE
A134: CENTRAL1 | B134: 3050 | C134: MSG AVISO | D134: ABC
...

Sheet AUTH_COGNITO
B1: ADMIN: Activacion Aplicación Individual 1x1
A2: 1 | B2: Servicio para consultar participantes de una empresa, con los datos: idempresa, idpartipante, nombre, correo(blanco), ESTATUS(0)
A3: 1 | B3: Selecciona un participante, le captura un email y selecciona CONTINUAR
A4: 1.1 | B4: Se consume servicio para Activar pariticipante
A5: 2 | B5: Se verifica si el email no exista en PARTICIPANTE_AUTH, si no lo crea, genera IDUSUARIO_UNICO, se genera Codigo AC | H5: macastro@vector.com.mx | I5: 3e01db55-3f84-420f-aca5-031f07579b5b | J5: 912315
A6: 2.1 | B6: Se asocia el IDUSUARIO_UNICO a la idempresa-idparticipante
A7: 3 | B7: En la creacion o cambio de correo electronico, se envia correo de activacion al participante al correo que se registro
B9: ADMIN: Activacion Aplicación Masivo
A10: 1 | B10: El administrador tiene un XLS, con la relacion IDEMPRESA, IDPARTICIPANTE,email
A11: 2 | B11: El administrador importa el XLS y selecciona CONTINUAR
A12: 3 | B12: Pantalla de verificacion/conffirmacion, CONTINUAR
A13: 4 | B13: Se consume servicio para Activar pariticipantES
A14: 5 | B14: Se verifica por cada participante, que el email no exista en PARTICIPANTE_AUTH, si no lo crea, genera IDUSUARIO_UNICO, se genera Codigo AC | H14: macastro@vector.com.mx | I14: 3e01db55-3f84-420f-aca5-031f07579b5b | J14: 912315
A15: 5.1 | B15: Se asocia el IDUSUARIO_UNICO a la idempresa-idparticipante
A16: 6 | B16: En la creacion o cambio de correo electronico, se envia correo de activacion al participante al correo que se registro
B18: Registro Cognito
A19: 0 | B19: Captura: email, codigoactivacion, password, confirmacion password
A20: 1 | B20: Validar que el correo y idtokenunico que esta queriendo registrar exista en la BD participantes_auth
A21: 1.1 | B21: Si el correo a registrar no existe, presentar mensaje "El correo que intenta ingresa no se ecuentra registrado, contacta a tu administrador"
A22: 2 | B22: Se registra el correo en COGNITO, con sus credenciales ingresadas, se obtiene COGNITO-SUB y se registra en participantes_Auth
A23: 2.1 | B23: Registrar datos del dispositivo; generar identificador del dispositivo y almacenar en keychain
B25: Login
A26: 0 | B26: Captura: email, password, identificador dispositivo
A27: 1 | B27: COGNITO valida credenciales y nos entrega en JWT: Email, CONGNITO-SUB
A28: 1.1 | B28: Validar id dispositivo vs el registrado
A29: 2 | B29: Consume servicio de .NET para obtener relacion de empresas-partiipante, a partir del EMAIL-COGNITOSEC
B31: Resumen de contratos
A32: 1 | B32: Consumimos servicio AWS Resumen de contratos, se envia en HEADERS el JWT
A33: 2 | B33: Se entrega al front relacion de las empresas relacionadas en BD PARTICIPANTE | H33: {email, cognito-sec, empresas: [1-3050,1-3051,3-3551]} | J33: [{idorigen:1, idempresa:3051}, {idorigen:2, idempresa:3053}]
A34: 3 | B34: Se establece variable global en la app con el IDEMPRESA seleccionada
A35: 4 | B35: Se seleciona la 3051
B37: Consulta de Resumen de movimientos
A38: 1 | B38: Consumimos servicio AWS ejemplo Resumen Movimientos, se envia en HEADERS el JWT | H38: {autorization: barer | sesion:{2,3051,123456}}
A39: 1.1 | B39: /api/v1/movements? | H39: /api/v1/movements?
A40: =A38+1 -> 2 | B40: Se valida en AWS JWT vs COGNITO (LAMBDA)
A41: =A40+1 -> 3 | B41: Una vez autorizado por COGNITO, se consume servicio de .NET | H41: {
A42: 3.1 | B42: Cognito valida sesion valida (expiracion, vigencia, etc)?
A43: =A41+1 -> 4 | B43: AWS LAMBDA recibe por headers: JWT; | E43: se recibe tambien appversion, ip, geolocalizacion, osversion, ostype (andr/ios), canal (web/movil), phonemodel
A44: 4.1 | B44: AWS LAMBDA valida que no exista bloqueo de acceso a nivel global (dynamodb.DAHSBOARD_CONF_PARAMS)
A45: 4.2 | B45: AWS LAMBDA verficar version vigente app android/ios (dynamodb.DAHSBOARD_CONF_PARAMS)
A46: =A43+1 -> 5 | B46: AWS LAMBDA valida que exista esa relacion (dynamo.PARTICIPANTE_AUTH | REL_ORIGEN_EMPRESA_PARTICIPANTE_USUARIOUNICO)
A47: 5.1 | B47: AWS LAMBDA valida que la empresa se encuentra Activa, no exista bloqueo de acceso a nivel empresa a consultar (dynam.DAHSBOARD_CONF_PARAMS_EMP)
A48: 5.2 | B48: AWS LAMBDA que el usuario tenga acceso al servicio (dynamo.PERFIL-IDSERVICIO | SERVICIO)
A49: 5.2 | B49: AWS LAMBDA finnaly se genera bitacora de acceso: elemento, usuario, fecha, hora, tiempo ejecucion etc (dynamo.BITACORAAPP)
A50: =A46+1 -> 6 | B50: Entregamos la informacion que esta alojada en DYBAMODB | H50: warning: "No encontramos en proceso de actualizacion de saldo…."
H51: data: {}
B52: Cerrar sesion | H52: }
A53: 1 | B53: Consumir servicio de cognito para cerrar sesion

Sheet PANTALLA DASHBOARD INI
B1: IDEMPRESA | C1: NOMBRE | D1: TIPO | E1: FECHA VALUACION | F1: NO.CONTRATO
B2: 351 | C2: CAHPAT | D2: Caja Ahorro | E2: 45772 | F2: 171365
B3: 213 | C3: FONDO EMPLEADOS | D3: Fondo | E3: 45772 | F3: 121312
B4: 513 | C4: Pensiones | D4: Pensiones | E4: 45772 | F4: 151613

Sheet BITACORA_TABLE
A1: FECHA | B1: HORA | C1: USUARIO | D1: PERFIL | E1: IDELEMENTO | F1: ELEMENTO | G1: IP | H1: GEO LAT | I1: GEO LON | J1: TIEMPO EJECUSION | K1: PARAMS | L1: ESTATUS PETICION
A2: 45776 | B2: 0.66666667 | C2: macastro@vector.com.mx | D2: SISTEMAS | E2: 10100 | F2: SERVICIO X | G2: 192.168.1.15 | H2: 12313213 | I2: 12313213 | J2: 3 | K2: abc | L2: 200
A3: 45776 | B3: 0.66666667 | C3: macastro@vector.com.mx | D3: SISTEMAS | E3: 10110 | F3: SERVICIO Y | G3: 192.168.1.15 | H3: 12313213 | I3: 12313213 | J3: 1 | K3: abc | L3: 200
A4: 45776 | B4: 0.66666667 | C4: macastro@vector.com.mx | D4: SISTEMAS | E4: 10400 | F4: SERVICIO Z | G4: 192.168.1.15 | H4: 12313213 | I4: 12313213 | J4: 4 | K4: abc | L4: 200

Sheet RECURSOS
A1: RECURSO | B1: TIPO | C1: ASIG | D1: DETALLE | E1: PROV
A2: BACKEND1 | B2: .NET | C2: ¿? | D2: IIS, SQLSERVER | E2: AXEN/NUEVO INTERNO
A3: BACKEND2 | B3: AWS | C3: ¿? | D3: API GATEWAY/LMABDA/COGNITO/RDS/DYNAMO | E3: ¿?
A4: FRONTEND1 | B4: REACT/REACT-NATIVE | C4: ¿? | D4: WEBDEVELOP | E4: ¿?

Sheet JIRA
A1: EPIC LINK | B1: SUMMARY | C1: Story Points
A2: RVPM-154 | B2: =_xlfn.CONCAT("[",ACTIVIDADES!A2,"] [",ACTIVIDADES!C2,"] ",ACTIVIDADES!I2," (",ACTIVIDADES!B2,")") -> [GENERAL] [BACK] Script para dar de alta SuperUsurio para Adminisitrar Adminsitradores (AWS) | C2: =ACTIVIDADES!K2 -> 8
A3: RVPM-154 | B3: =_xlfn.CONCAT("[",ACTIVIDADES!A3,"] [",ACTIVIDADES!C3,"] ",ACTIVIDADES!I3," (",ACTIVIDADES!B3,")") -> [GENERAL] [BACK] Script para generar estructuras de tablas nuevas de base de datos y carga inicial de datos y catalogos (AWS) | C3: =ACTIVIDADES!K3 -> 20
A4: RVPM-154 | B4: =_xlfn.CONCAT("[",ACTIVIDADES!A4,"] [",ACTIVIDADES!C4,"] ",ACTIVIDADES!I4," (",ACTIVIDADES!B4,")") -> [GENERAL] [BACK] Ruteo de peticiones REST a distintas base de datos dependiendo del Origen solicitado (.NET) | C4: =ACTIVIDADES!K4 -> 16
A5: RVPM-154 | B5: =_xlfn.CONCAT("[",ACTIVIDADES!A5,"] [",ACTIVIDADES!C5,"] ",ACTIVIDADES!I5," (",ACTIVIDADES!B5,")") -> [GENERAL] [BACK] Preparar nuevo PROYECTO para este set de servicios (AWS) | C5: =ACTIVIDADES!K5 -> 8
A6: RVPM-154 | B6: =_xlfn.CONCAT("[",ACTIVIDADES!A6,"] [",ACTIVIDADES!C6,"] ",ACTIVIDADES!I6," (",ACTIVIDADES!B6,")") -> [GENERAL] [BACK] Preparar ejemplo de servicio base GET/PUT/POST/DEL, con manejo de sesion JWT, validaciones y bitacora; para replicar en el universo de servicios (.NET) | C6: =ACTIVIDADES!K6 -> 16
A7: RVPM-154 | B7: =_xlfn.CONCAT("[",ACTIVIDADES!A7,"] [",ACTIVIDADES!C7,"] ",ACTIVIDADES!I7," (",ACTIVIDADES!B7,")") -> [GENERAL] [ARQ] Preparar proceso asincrono para generar archivo JSON de empresa SOLO para la empresa con bandera ACTIVOAPP true (JAVA) (.NET) | C7: =ACTIVIDADES!K7 -> 20
A8: RVPM-154 | B8: =_xlfn.CONCAT("[",ACTIVIDADES!A8,"] [",ACTIVIDADES!C8,"] ",ACTIVIDADES!I8," (",ACTIVIDADES!B8,")") -> [GENERAL] [BACK] Realizar envio de archivo JSON a bucket S3 AWS de empresas (.NET) | C8: =ACTIVIDADES!K8 -> 20
A9: RVPM-154 | B9: =_xlfn.CONCAT("[",ACTIVIDADES!A9,"] [",ACTIVIDADES!C9,"] ",ACTIVIDADES!I9," (",ACTIVIDADES!B9,")") -> [GENERAL] [BACK] Prepara CDK cdk-apisvector-pai: apigateway, lambdas, sqs, s3 (AWS) | C9: =ACTIVIDADES!K9 -> 8
A10: RVPM-154 | B10: =_xlfn.CONCAT("[",ACTIVIDADES!A10,"] [",ACTIVIDADES!C10,"] ",ACTIVIDADES!I10," (",ACTIVIDADES!B10,")") -> [GENERAL] [BACK] Prepara CDK cdk-apisvector-pai: estructuras de tablas dynamodb, json empresa; estatus proceso sqs, etc (AWS) | C10: =ACTIVIDADES!K10 -> 8
A11: RVPM-154 | B11: =_xlfn.CONCAT("[",ACTIVIDADES!A11,"] [",ACTIVIDADES!C11,"] ",ACTIVIDADES!I11," (",ACTIVIDADES!B11,")") -> [GENERAL] [BACK] Prepara CDK cdk-apisvector-pai: apigateway's domain vectorpai.api.vectordev.com.mx (AWS) | C11: =ACTIVIDADES!K11 -> 8
A12: RVPM-154 | B12: =_xlfn.CONCAT("[",ACTIVIDADES!A12,"] [",ACTIVIDADES!C12,"] ",ACTIVIDADES!I12," (",ACTIVIDADES!B12,")") -> [GENERAL] [BACK] Prepara CDK cdk-apisvector-pai: CID con workflow de git (Continuous integration deployment) (AWS) | C12: =ACTIVIDADES!K12 -> 16
A13: RVPM-154 | B13: =_xlfn.CONCAT("[",ACTIVIDADES!A13,"] [",ACTIVIDADES!C13,"] ",ACTIVIDADES!I13," (",ACTIVIDADES!B13,")") -> [GENERAL] [BACK] Configuracion de correos de codigo de activacion y codigo de confirmacion, templates (AWS) | C13: =ACTIVIDADES!K13 -> 16
... A156: RVPM-154 | B156: =_xlfn.CONCAT("[",ACTIVIDADES!A156,"] [",ACTIVIDADES!C156,"] ",ACTIVIDADES!I156," (",ACTIVIDADES!B156,")") -> [] [] () | C156: =ACTIVIDADES!K156 -> 0
